AUTHORS
LICENSE
MANIFEST.in
README.rst
setup.py
django_json_field.egg-info/PKG-INFO
django_json_field.egg-info/SOURCES.txt
django_json_field.egg-info/dependency_links.txt
django_json_field.egg-info/requires.txt
django_json_field.egg-info/top_level.txt
json_field/__init__.py
json_field/fields.py
json_field/forms.py
json_field/models.py
json_field/tests.py
json_field/utils.py
json_field/views.py