Metadata-Version: 1.0
Name: django-json-field
Version: 0.5.4
Summary: Generic JSON model and form fields.
Home-page: https://github.com/derek-schaefer/django-json-field
Author: Derek Schaefer
Author-email: derek.schaefer@gmail.com
License: UNKNOWN
Platform: UNKNOWN
Classifier: Development Status :: 3 - Alpha
Classifier: Intended Audience :: Developers
Classifier: License :: OSI Approved :: BSD License
Classifier: Operating System :: OS Independent
Classifier: Programming Language :: Python
Classifier: Topic :: Software Development :: Libraries :: Python Modules
